unwrap/__init__.py
unwrap/_cffi__x26510b16x3b92e2f4.so
unwrap/_cffi__x30a54445x43bc0d6d.so
unwrap/unwrap.py
unwrap/unwrap2D.c
unwrap/unwrap2D.py
unwrap/unwrap3D.c
unwrap/unwrap3D.py
unwrap-0.1.1.dist-info/DESCRIPTION.rst
unwrap-0.1.1.dist-info/METADATA
unwrap-0.1.1.dist-info/pydist.json
unwrap-0.1.1.dist-info/RECORD
unwrap-0.1.1.dist-info/top_level.txt
unwrap-0.1.1.dist-info/WHEEL
