Metadata-Version: 2.0
Name: unwrap
Version: 0.1.1
Summary: 2D and 3D phase unwrapping
Home-page: http://github.com/geggo/phase-unwrap
Author: Gregor Thalhammer
Author-email: gregor.thalhammer@gmail.com
License: UNKNOWN
Platform: UNKNOWN
Classifier: Development Status :: 4 - Beta
Classifier: Intended Audience :: Science/Research
Classifier: License :: OSI Approved :: MIT License
Classifier: Programming Language :: Python
Classifier: Programming Language :: Python :: 2
Classifier: Programming Language :: Python :: 3
Classifier: Topic :: Scientific/Engineering
Classifier: Operating System :: OS Independent
Provides: unwrap
Requires-Dist: numpy (>=1.6)
Requires-Dist: cffi (>=0.7)
